cVQE/__init__.py
cVQE/initial_states/__init__.py
cVQE/initial_states/compressed_zero.py
cVQE/operators/__init__.py
cVQE/operators/converters/__init__.py
cVQE/operators/converters/quadratic_operator_reducer.py
cVQE/operators/converters/quadratric_operator_reducer.py
cVQE/operators/converters/tensoredop_distributor.py
cVQE/operators/converters/zero_coeff_nuller.py
cVQE/variational_forms/__init__.py
cVQE/variational_forms/cfgs.py
cVQE-0.0.2.dist-info/LICENSE
cVQE-0.0.2.dist-info/METADATA
cVQE-0.0.2.dist-info/WHEEL
cVQE-0.0.2.dist-info/top_level.txt
cVQE-0.0.2.dist-info/RECORD
